healthcheckx/__init__.py
healthcheckx/check.py
healthcheckx/core.py
healthcheckx/exceptions.py
healthcheckx/result.py
healthcheckx/adapters/__init__.py
healthcheckx/adapters/django.py
healthcheckx/adapters/fastapi.py
healthcheckx/adapters/flask.py
healthcheckx/checks/cache/__init__.py
healthcheckx/checks/cache/keydb_check.py
healthcheckx/checks/cache/memcached_check.py
healthcheckx/checks/cache/redis_check.py
healthcheckx/checks/messageQueue/__init__.py
healthcheckx/checks/messageQueue/activemq_check.py
healthcheckx/checks/messageQueue/kafka_check.py
healthcheckx/checks/messageQueue/rabbitmq_check.py
healthcheckx/checks/nosqlDB/__init__.py
healthcheckx/checks/nosqlDB/mongodb_check.py
healthcheckx/checks/relationalDB/__init__.py
healthcheckx/checks/relationalDB/mssql_check.py
healthcheckx/checks/relationalDB/mysql_check.py
healthcheckx/checks/relationalDB/oracle_check.py
healthcheckx/checks/relationalDB/postgresql_check.py
healthcheckx/checks/relationalDB/sqlite_check.py
healthcheckx-1.2.0.dist-info/licenses/LICENSE
healthcheckx-1.2.0.dist-info/METADATA
healthcheckx-1.2.0.dist-info/WHEEL
healthcheckx-1.2.0.dist-info/top_level.txt
healthcheckx-1.2.0.dist-info/RECORD
