Metadata-Version: 2.4
Name: healthcheckx
Version: 1.2.0
Summary: Production-grade health checks for Python applications
Author-email: Soumen Samanta <you@example.com>
License: MIT License
Project-URL: Documentation, https://soumen3.github.io/healthcheckx/
Project-URL: Homepage, https://soumen3.github.io/healthcheckx/
Project-URL: Repository, https://github.com/Soumen3/healthcheckx
Project-URL: Issues, https://github.com/Soumen3/healthcheckx/issues
Classifier: Programming Language :: Python :: 3
Classifier: Programming Language :: Python :: 3 :: Only
Classifier: License :: OSI Approved :: MIT License
Classifier: Operating System :: OS Independent
Classifier: Topic :: System :: Monitoring
Classifier: Topic :: Internet :: WWW/HTTP
Requires-Python: >=3.8
License-File: LICENSE
Provides-Extra: redis
Requires-Dist: redis>=5.0; extra == "redis"
Provides-Extra: memcached
Requires-Dist: pymemcache>=4.0; extra == "memcached"
Provides-Extra: rabbitmq
Requires-Dist: pika>=1.3; extra == "rabbitmq"
Provides-Extra: kafka
Requires-Dist: kafka-python>=2.0; extra == "kafka"
Provides-Extra: activemq
Requires-Dist: stomp.py>=8.0; extra == "activemq"
Provides-Extra: postgresql
Requires-Dist: psycopg2-binary>=2.9; extra == "postgresql"
Provides-Extra: mysql
Requires-Dist: mysql-connector-python>=8.0; extra == "mysql"
Provides-Extra: oracle
Requires-Dist: oracledb>=3.4; extra == "oracle"
Provides-Extra: mssql
Requires-Dist: pymssql>=2.2; extra == "mssql"
Provides-Extra: mongodb
Requires-Dist: pymongo>=4.0; extra == "mongodb"
Provides-Extra: all
Requires-Dist: redis>=5.0; extra == "all"
Requires-Dist: pymemcache>=4.0; extra == "all"
Requires-Dist: pika>=1.3; extra == "all"
Requires-Dist: kafka-python>=2.0; extra == "all"
Requires-Dist: stomp.py>=8.0; extra == "all"
Requires-Dist: psycopg2-binary>=2.9; extra == "all"
Requires-Dist: mysql-connector-python>=8.0; extra == "all"
Requires-Dist: oracledb>=3.4; extra == "all"
Requires-Dist: pymssql>=2.2; extra == "all"
Requires-Dist: pymongo>=4.0; extra == "all"
Dynamic: license-file
